{
  "name": "Waterfall Token List",
  "timestamp": "2022-07-10T18:08:00.164591Z",
  "keywords": [
    "null"
  ],
  "logoURI": "ipfs://QmQAGtNJ2rSGpnP6dh6PPKNSmZL8RTZXmgFwgTdy5Nz5mx",
  "version": {
    "major": 5,
    "minor": 0,
    "patch": 0
  },
  "tokens": [
    {
      "chainId": 333777333,
      "name": "WEETH",
      "address": "0x9954f4f6F20C63c30dF1107Fc26126dc3347c91E",
      "decimals": 18,
      "symbol": "WEETH",
      "logoURI": "https://explorer.waterfall.network/favicon-72-precomposed.png"
    },
    {
      "chainId": 333777333,
      "name": "WBBNB",
      "address": "0x6Ad0550e01EAD1CE0D75E25329eABAf46C95D8A2",
      "decimals": 18,
      "symbol": "WBBNB",
      "logoURI": "https://explorer.waterfall.network/favicon-72-precomposed.png"
    }
  ]
}
